.gitignore
AUTHORS.txt
CHANGES.txt
COPYING.txt
MANIFEST.in
README.rst
README.txt
development.ini
i18n.sh
setup.cfg
setup.py
kotti_site_gallery/__init__.py
kotti_site_gallery/resources.py
kotti_site_gallery/views.py
kotti_site_gallery.egg-info/PKG-INFO
kotti_site_gallery.egg-info/SOURCES.txt
kotti_site_gallery.egg-info/dependency_links.txt
kotti_site_gallery.egg-info/entry_points.txt
kotti_site_gallery.egg-info/not-zip-safe
kotti_site_gallery.egg-info/requires.txt
kotti_site_gallery.egg-info/top_level.txt
kotti_site_gallery/locale/kotti_site_gallery.pot
kotti_site_gallery/locale/de/LC_MESSAGES/kotti_site_gallery.mo
kotti_site_gallery/locale/de/LC_MESSAGES/kotti_site_gallery.po
kotti_site_gallery/locale/en/LC_MESSAGES/kotti_site_gallery.mo
kotti_site_gallery/locale/en/LC_MESSAGES/kotti_site_gallery.po
kotti_site_gallery/static/kotti_site_gallery.css
kotti_site_gallery/static/kotti_site_gallery.min.css
kotti_site_gallery/templates/site-gallery-view.pt
kotti_site_gallery/templates/site-view.pt
kotti_site_gallery/tests/browser.txt
kotti_site_gallery/tests/conftest.py
kotti_site_gallery/tests/test_site.py