Metadata-Version: 1.1
Name: kotti-site-gallery
Version: 0.2.0
Summary: Site gallery for Kotti sites
Home-page: http://pypi.python.org/pypi/kotti_site_gallery
Author: Kotti developers
Author-email: kotti@googlegroups.com
License: BSD-2-Clause
Keywords: kotti site gallery
Platform: UNKNOWN
Classifier: Development Status :: 4 - Beta
Classifier: Programming Language :: Python
Classifier: Framework :: Pylons
Classifier: Topic :: Internet :: WWW/HTTP
Classifier: Topic :: Internet :: WWW/HTTP :: Dynamic Content
Classifier: Topic :: Internet :: WWW/HTTP :: WSGI :: Application
Classifier: License :: OSI Approved :: BSD License
